{
  "cards": [
    {
      "id": 1,
      "name": "Ремонт мобільних телефонів",
      "phone": "(066)033-32-26",
      "сity": "Korostyshiv",
    },
    {
      "id": 2,
      "name": "Ремонт електроніки і побутової техніки",
      "phone": "(099)530-85-87",
      "сity": "Korostyshiv",
    },
    {
      "id": 3,
      "name": "Пасажирські перевезення",
      "phone": "(099)333-29-33",
      "сity": "Korostyshiv",
    },
    {
      "id": 4,
      "name": "Ваше таксі",
      "phone": "(066)639-36-83",
      "сity": "Korostyshiv",
    },
    {
      "id": 5,
      "name": "Ремонт електроніки і побутової техніки",
      "phone": "(099)530-85-87",
      "сity": "Korostyshiv",
    },
    {
      "id": 6,
      "name": "Масаж і процедури",
      "phone": "(067)337-63-15",
      "сity": "Korostyshiv",
    },
    {
      "id": 7,
      "name": "Ветеринарні послуги",
      "phone": "(067)760-03-76",
      "сity": "Korostyshiv",
    },
    {
      "id": 8,
      "name": "Кури Ґриль",
      "phone": "(096)884-55-41",
      "сity": "Korostyshiv",
    },
    {
      "id": 9,
      "name": "Таксі Ґлорія",
      "phone": "(098)116-01-36",
      "сity": "Korostyshiv",
    },
    {
      "id": 10,
      "name": "Магазин Марафет",
      "phone": "(096)11-00-772",
      "сity": "Korostyshiv",
    },
    {
      "id": 11,
      "name": "Сантехнічні роботи",
      "phone": "(097)986-75-63",
      "сity": "Korostyshiv",
    },
    {
      "id": 12,
      "name": "Ремонт та обслуговування  комп`ютерної техніки",
      "phone": "(099)146-42-60",
      "сity": "Korostyshiv",
    }

     ]
}